<?xml version="1.0" encoding="utf-8" ?>
<c2eventsheet>
    <!--All the 'name' attributes are ignored by Construct 2 - they are there for readability only.-->
    <name>Main</name>
    <events>
        <include>Globals and Constants</include>
        <include>Creation</include>
        <include>Common</include>
        <include>Player</include>
        <include>Humans</include>
        <include>Electrodes</include>
        <include>Grunts</include>
        <include>Hulk</include>
        <include>Brains</include>
        <include>Quark, Spheroid, Enforcer, Tank</include>
        <include>Missiles</include>
    </events>
</c2eventsheet>
